{"GlobalPropertiesHash":"kkfR5qTfUSHfGdk2zNmznuoO/F82B1JTTwRDa/UynfA=","FingerprintPatternsHash":"gq3WsqcKBUGTSNle7RKKyXRIwh7M8ccEqOqYvIzoM04=","PropertyOverridesHash":"8ZRc1sGeVrPBx4lD717BgRaQekyh78QKV9SKsdt638U=","InputHashes":["srVuSqGGQiy1\u002BjiLI5Dbs5KLt61gg8k5RspcUpwNVf8=","fH0XY2dPkhZqJ2CT73m92UX/OfEzUfGuPj7bus6PpZE=","UwiOoye3wR1BraaIGetbJr/GBibAJJWWdsfrVfpi8Pg=","XkLQ\u002BvAKJO\u002BGW4flwyNMxSds1bPPmjq6agFVbm6PdDI=","wbPz38gtySDOUtUbH8isy1PAXy/bM5Bym\u002BQHzEU1KAM=","RPyn46MGx2xUv5imEz00tm2ljnGm4xH2wy63YqTRgpw=","CWR9o1b8H/KrOx4B6y59Jc7D59XzujUpzZpDg674k/Q=","0q9mp5hCYN1wrp8y3THBeLVLwbjX1v\u002BdFfWa\u002B9ZdQNY=","dU706pxyX3H3QZ5rDJGOhxqQ5r7Ed5IHsbAZJ0fCbDs=","ztGJJBcjDWIyAQWgMN6htdCZJ30B0AdXI64/5GanZus=","n92v3U0IyM1N6UcS85yhXau89Hn4r9GamADXzMTbMxM=","qQX5WE3O19I/Z6gQZx3ecQdsdiG42Ag\u002BrZ/tKbagWOY=","\u002B\u002B7oypelu9WeychMy56TtSZqnGL9YDtIfMJbyaNiPn8=","ADM6EkwwkzJQTMP3WqV\u002BpCCC8JUlGbe7sIUaukYGr\u002BI=","ZLE003KkNpHkxs4Mq4Jz3mcLIip3\u002BD2C3DWy3p8JDZU=","Sv7U6iagZXLI1p7GPVz3LAL8nCai7WWpXWHwJsSPB/E=","qgBhOCuk73FmUWbTmT\u002ByP6oRuBRE2OKpz5Ai9EviJGs=","RYx8y9qJ0pKv7ixoVqRXzPsrSLOfS0TU0C9T7ip4xec=","/1RFMXEsx9sR5WAzQ675k0\u002BDZa2GQjY63ebli8Vjl8s=","MGmue4x\u002BrpvnPa/VVYKaS4vkQ8PMjOJDIlGz9dvIfyE=","u57XUa99chEmVpTxh26bOZIegPFwimNvJ60TM\u002BVYBXc=","SSlbA6/NIvWRlmKt8Mz0gxnkWsNHWwNZFRV0uepe0\u002B8="],"CachedAssets":{"RPyn46MGx2xUv5imEz00tm2ljnGm4xH2wy63YqTRgpw=":{"Identity":"D:\\VSporjects\\Recipix\\Recipix.Server\\wwwroot\\images\\borsch.jpg","SourceId":"Recipix.Server","SourceType":"Discovered","ContentRoot":"D:\\VSporjects\\Recipix\\Recipix.Server\\wwwroot\\","BasePath":"_content/Recipix.Server","RelativePath":"images/borsch#[.{fingerprint}]?.jpg","AssetKind":"All","AssetMode":"All","AssetRole":"Primary","AssetMergeBehavior":null,"AssetMergeSource":"","RelatedAsset":null,"AssetTraitName":null,"AssetTraitValue":null,"Fingerprint":"cvqvb4pb86","Integrity":"OJtfgKYWqymys7g/1qSQ2oqZGe/DPkGCYFS9yeJrd4k=","CopyToOutputDirectory":"Never","CopyToPublishDirectory":"PreserveNewest","OriginalItemSpec":"wwwroot\\images\\borsch.jpg","FileLength":97734,"LastWriteTime":"2025-07-09T10:01:11.9877+00:00"},"CWR9o1b8H/KrOx4B6y59Jc7D59XzujUpzZpDg674k/Q=":{"Identity":"D:\\VSporjects\\Recipix\\Recipix.Server\\wwwroot\\images\\omlet.jpeg","SourceId":"Recipix.Server","SourceType":"Discovered","ContentRoot":"D:\\VSporjects\\Recipix\\Recipix.Server\\wwwroot\\","BasePath":"_content/Recipix.Server","RelativePath":"images/omlet#[.{fingerprint}]?.jpeg","AssetKind":"All","AssetMode":"All","AssetRole":"Primary","AssetMergeBehavior":null,"AssetMergeSource":"","RelatedAsset":null,"AssetTraitName":null,"AssetTraitValue":null,"Fingerprint":"fjx5rvew8w","Integrity":"C/AExtp8HEdOYz0D6JD7rEJm4GoQnK/IuoqXpilckgk=","CopyToOutputDirectory":"Never","CopyToPublishDirectory":"PreserveNewest","OriginalItemSpec":"wwwroot\\images\\omlet.jpeg","FileLength":7280,"LastWriteTime":"2025-07-09T10:09:29.4455251+00:00"},"0q9mp5hCYN1wrp8y3THBeLVLwbjX1v\u002BdFfWa\u002B9ZdQNY=":{"Identity":"D:\\VSporjects\\Recipix\\Recipix.Server\\wwwroot\\images\\pasta.jpeg","SourceId":"Recipix.Server","SourceType":"Discovered","ContentRoot":"D:\\VSporjects\\Recipix\\Recipix.Server\\wwwroot\\","BasePath":"_content/Recipix.Server","RelativePath":"images/pasta#[.{fingerprint}]?.jpeg","AssetKind":"All","AssetMode":"All","AssetRole":"Primary","AssetMergeBehavior":null,"AssetMergeSource":"","RelatedAsset":null,"AssetTraitName":null,"AssetTraitValue":null,"Fingerprint":"4m99ibuwuz","Integrity":"FCmB3JCuSHLWohOSekrguICvwYQFRNX88VR9tsT\u002BgSY=","CopyToOutputDirectory":"Never","CopyToPublishDirectory":"PreserveNewest","OriginalItemSpec":"wwwroot\\images\\pasta.jpeg","FileLength":9681,"LastWriteTime":"2025-07-09T10:09:49.2785176+00:00"},"wbPz38gtySDOUtUbH8isy1PAXy/bM5Bym\u002BQHzEU1KAM=":{"Identity":"D:\\VSporjects\\Recipix\\Recipix.Server\\wwwroot\\avatars\\defaultpfp.png","SourceId":"Recipix.Server","SourceType":"Discovered","ContentRoot":"D:\\VSporjects\\Recipix\\Recipix.Server\\wwwroot\\","BasePath":"_content/Recipix.Server","RelativePath":"avatars/defaultpfp#[.{fingerprint}]?.png","AssetKind":"All","AssetMode":"All","AssetRole":"Primary","AssetMergeBehavior":null,"AssetMergeSource":"","RelatedAsset":null,"AssetTraitName":null,"AssetTraitValue":null,"Fingerprint":"afs93s2w3c","Integrity":"2hRJvmDxZUGjAnsiXpZZqXjkMis25HRgMvotaD/nfCw=","CopyToOutputDirectory":"Never","CopyToPublishDirectory":"PreserveNewest","OriginalItemSpec":"wwwroot\\avatars\\defaultpfp.png","FileLength":13650,"LastWriteTime":"2025-07-11T16:52:21.2845118+00:00"},"srVuSqGGQiy1\u002BjiLI5Dbs5KLt61gg8k5RspcUpwNVf8=":{"Identity":"D:\\VSporjects\\Recipix\\Recipix.Server\\wwwroot\\avatars\\avatar_3.png","SourceId":"Recipix.Server","SourceType":"Discovered","ContentRoot":"D:\\VSporjects\\Recipix\\Recipix.Server\\wwwroot\\","BasePath":"_content/Recipix.Server","RelativePath":"avatars/avatar_3#[.{fingerprint}]?.png","AssetKind":"All","AssetMode":"All","AssetRole":"Primary","AssetMergeBehavior":null,"AssetMergeSource":"","RelatedAsset":null,"AssetTraitName":null,"AssetTraitValue":null,"Fingerprint":"1h41yz289t","Integrity":"G0WmNmS3Jhn3BTjgmUqLc1v58LXZA3bnIToH78O\u002B6tM=","CopyToOutputDirectory":"Never","CopyToPublishDirectory":"PreserveNewest","OriginalItemSpec":"wwwroot\\avatars\\avatar_3.png","FileLength":124823,"LastWriteTime":"2025-07-12T15:06:16.6135284+00:00"},"/1RFMXEsx9sR5WAzQ675k0\u002BDZa2GQjY63ebli8Vjl8s=":{"Identity":"D:\\VSporjects\\Recipix\\Recipix.Server\\wwwroot\\recipe-images\\a656b481-f601-4882-afae-a6ff1d9325d6.png","SourceId":"Recipix.Server","SourceType":"Discovered","ContentRoot":"D:\\VSporjects\\Recipix\\Recipix.Server\\wwwroot\\","BasePath":"_content/Recipix.Server","RelativePath":"recipe-images/a656b481-f601-4882-afae-a6ff1d9325d6#[.{fingerprint}]?.png","AssetKind":"All","AssetMode":"All","AssetRole":"Primary","AssetMergeBehavior":null,"AssetMergeSource":"","RelatedAsset":null,"AssetTraitName":null,"AssetTraitValue":null,"Fingerprint":"1lbbteido1","Integrity":"ZaTIeoezyJ0YNPG8E/EQaNhygnbxouKzT/LamOhfDww=","CopyToOutputDirectory":"Never","CopyToPublishDirectory":"PreserveNewest","OriginalItemSpec":"wwwroot\\recipe-images\\a656b481-f601-4882-afae-a6ff1d9325d6.png","FileLength":255066,"LastWriteTime":"2025-07-13T16:24:35.9868042+00:00"},"qQX5WE3O19I/Z6gQZx3ecQdsdiG42Ag\u002BrZ/tKbagWOY=":{"Identity":"D:\\VSporjects\\Recipix\\Recipix.Server\\wwwroot\\recipe-images\\4ae13fb8-6223-4d6f-80d1-5a25373a926d.png","SourceId":"Recipix.Server","SourceType":"Discovered","ContentRoot":"D:\\VSporjects\\Recipix\\Recipix.Server\\wwwroot\\","BasePath":"_content/Recipix.Server","RelativePath":"recipe-images/4ae13fb8-6223-4d6f-80d1-5a25373a926d#[.{fingerprint}]?.png","AssetKind":"All","AssetMode":"All","AssetRole":"Primary","AssetMergeBehavior":null,"AssetMergeSource":"","RelatedAsset":null,"AssetTraitName":null,"AssetTraitValue":null,"Fingerprint":"1lbbteido1","Integrity":"ZaTIeoezyJ0YNPG8E/EQaNhygnbxouKzT/LamOhfDww=","CopyToOutputDirectory":"Never","CopyToPublishDirectory":"PreserveNewest","OriginalItemSpec":"wwwroot\\recipe-images\\4ae13fb8-6223-4d6f-80d1-5a25373a926d.png","FileLength":255066,"LastWriteTime":"2025-07-13T16:24:40.3571285+00:00"},"ZLE003KkNpHkxs4Mq4Jz3mcLIip3\u002BD2C3DWy3p8JDZU=":{"Identity":"D:\\VSporjects\\Recipix\\Recipix.Server\\wwwroot\\recipe-images\\8960fca4-190e-4e97-ae9f-ed49259569dd.png","SourceId":"Recipix.Server","SourceType":"Discovered","ContentRoot":"D:\\VSporjects\\Recipix\\Recipix.Server\\wwwroot\\","BasePath":"_content/Recipix.Server","RelativePath":"recipe-images/8960fca4-190e-4e97-ae9f-ed49259569dd#[.{fingerprint}]?.png","AssetKind":"All","AssetMode":"All","AssetRole":"Primary","AssetMergeBehavior":null,"AssetMergeSource":"","RelatedAsset":null,"AssetTraitName":null,"AssetTraitValue":null,"Fingerprint":"1lbbteido1","Integrity":"ZaTIeoezyJ0YNPG8E/EQaNhygnbxouKzT/LamOhfDww=","CopyToOutputDirectory":"Never","CopyToPublishDirectory":"PreserveNewest","OriginalItemSpec":"wwwroot\\recipe-images\\8960fca4-190e-4e97-ae9f-ed49259569dd.png","FileLength":255066,"LastWriteTime":"2025-07-13T16:29:43.4341632+00:00"},"n92v3U0IyM1N6UcS85yhXau89Hn4r9GamADXzMTbMxM=":{"Identity":"D:\\VSporjects\\Recipix\\Recipix.Server\\wwwroot\\recipe-images\\487f504f-72c2-430f-aa9e-1332268f2579.png","SourceId":"Recipix.Server","SourceType":"Discovered","ContentRoot":"D:\\VSporjects\\Recipix\\Recipix.Server\\wwwroot\\","BasePath":"_content/Recipix.Server","RelativePath":"recipe-images/487f504f-72c2-430f-aa9e-1332268f2579#[.{fingerprint}]?.png","AssetKind":"All","AssetMode":"All","AssetRole":"Primary","AssetMergeBehavior":null,"AssetMergeSource":"","RelatedAsset":null,"AssetTraitName":null,"AssetTraitValue":null,"Fingerprint":"1lbbteido1","Integrity":"ZaTIeoezyJ0YNPG8E/EQaNhygnbxouKzT/LamOhfDww=","CopyToOutputDirectory":"Never","CopyToPublishDirectory":"PreserveNewest","OriginalItemSpec":"wwwroot\\recipe-images\\487f504f-72c2-430f-aa9e-1332268f2579.png","FileLength":255066,"LastWriteTime":"2025-07-13T16:33:36.396083+00:00"},"RYx8y9qJ0pKv7ixoVqRXzPsrSLOfS0TU0C9T7ip4xec=":{"Identity":"D:\\VSporjects\\Recipix\\Recipix.Server\\wwwroot\\recipe-images\\a4e25189-11d2-4717-a209-fc8794d9465a.png","SourceId":"Recipix.Server","SourceType":"Discovered","ContentRoot":"D:\\VSporjects\\Recipix\\Recipix.Server\\wwwroot\\","BasePath":"_content/Recipix.Server","RelativePath":"recipe-images/a4e25189-11d2-4717-a209-fc8794d9465a#[.{fingerprint}]?.png","AssetKind":"All","AssetMode":"All","AssetRole":"Primary","AssetMergeBehavior":null,"AssetMergeSource":"","RelatedAsset":null,"AssetTraitName":null,"AssetTraitValue":null,"Fingerprint":"4zs092xn26","Integrity":"UKygm71mTh6l9QE4rZlaV6P4d5aH4lptNU430GZyAeQ=","CopyToOutputDirectory":"Never","CopyToPublishDirectory":"PreserveNewest","OriginalItemSpec":"wwwroot\\recipe-images\\a4e25189-11d2-4717-a209-fc8794d9465a.png","FileLength":767755,"LastWriteTime":"2025-07-13T16:35:53.0474677+00:00"},"dU706pxyX3H3QZ5rDJGOhxqQ5r7Ed5IHsbAZJ0fCbDs=":{"Identity":"D:\\VSporjects\\Recipix\\Recipix.Server\\wwwroot\\recipe-images\\01137544-4918-4ce0-8f4c-d307f1673e33.png","SourceId":"Recipix.Server","SourceType":"Discovered","ContentRoot":"D:\\VSporjects\\Recipix\\Recipix.Server\\wwwroot\\","BasePath":"_content/Recipix.Server","RelativePath":"recipe-images/01137544-4918-4ce0-8f4c-d307f1673e33#[.{fingerprint}]?.png","AssetKind":"All","AssetMode":"All","AssetRole":"Primary","AssetMergeBehavior":null,"AssetMergeSource":"","RelatedAsset":null,"AssetTraitName":null,"AssetTraitValue":null,"Fingerprint":"mn2ydk5c16","Integrity":"8o5Jyg4eYcwsN4/aIkKNC5jwUhWBAjIWlI6DsThuPp0=","CopyToOutputDirectory":"Never","CopyToPublishDirectory":"PreserveNewest","OriginalItemSpec":"wwwroot\\recipe-images\\01137544-4918-4ce0-8f4c-d307f1673e33.png","FileLength":334777,"LastWriteTime":"2025-07-13T16:48:49.5033869+00:00"},"MGmue4x\u002BrpvnPa/VVYKaS4vkQ8PMjOJDIlGz9dvIfyE=":{"Identity":"D:\\VSporjects\\Recipix\\Recipix.Server\\wwwroot\\recipe-images\\d9a29be1-bf5b-4d8b-beee-dcab299f1671.png","SourceId":"Recipix.Server","SourceType":"Discovered","ContentRoot":"D:\\VSporjects\\Recipix\\Recipix.Server\\wwwroot\\","BasePath":"_content/Recipix.Server","RelativePath":"recipe-images/d9a29be1-bf5b-4d8b-beee-dcab299f1671#[.{fingerprint}]?.png","AssetKind":"All","AssetMode":"All","AssetRole":"Primary","AssetMergeBehavior":null,"AssetMergeSource":"","RelatedAsset":null,"AssetTraitName":null,"AssetTraitValue":null,"Fingerprint":"15rwufzrv2","Integrity":"m0QhcVxu5fSi67fxEKRgf1gDsrD9CJtCUAkPw/dEMPk=","CopyToOutputDirectory":"Never","CopyToPublishDirectory":"PreserveNewest","OriginalItemSpec":"wwwroot\\recipe-images\\d9a29be1-bf5b-4d8b-beee-dcab299f1671.png","FileLength":1589619,"LastWriteTime":"2025-07-13T17:02:13.5083496+00:00"},"ADM6EkwwkzJQTMP3WqV\u002BpCCC8JUlGbe7sIUaukYGr\u002BI=":{"Identity":"D:\\VSporjects\\Recipix\\Recipix.Server\\wwwroot\\recipe-images\\70bc57e8-e5fb-46b7-aa33-fd2e9fadf751.png","SourceId":"Recipix.Server","SourceType":"Discovered","ContentRoot":"D:\\VSporjects\\Recipix\\Recipix.Server\\wwwroot\\","BasePath":"_content/Recipix.Server","RelativePath":"recipe-images/70bc57e8-e5fb-46b7-aa33-fd2e9fadf751#[.{fingerprint}]?.png","AssetKind":"All","AssetMode":"All","AssetRole":"Primary","AssetMergeBehavior":null,"AssetMergeSource":"","RelatedAsset":null,"AssetTraitName":null,"AssetTraitValue":null,"Fingerprint":"j0tvr0gttr","Integrity":"XSAu8Tq\u002BpGWhXgxI0vJrSGMN2U7OpMDyTDUE\u002BNh6acg=","CopyToOutputDirectory":"Never","CopyToPublishDirectory":"PreserveNewest","OriginalItemSpec":"wwwroot\\recipe-images\\70bc57e8-e5fb-46b7-aa33-fd2e9fadf751.png","FileLength":10815,"LastWriteTime":"2025-07-15T13:53:33.5391961+00:00"},"fH0XY2dPkhZqJ2CT73m92UX/OfEzUfGuPj7bus6PpZE=":{"Identity":"D:\\VSporjects\\Recipix\\Recipix.Server\\wwwroot\\avatars\\avatar_4.png","SourceId":"Recipix.Server","SourceType":"Discovered","ContentRoot":"D:\\VSporjects\\Recipix\\Recipix.Server\\wwwroot\\","BasePath":"_content/Recipix.Server","RelativePath":"avatars/avatar_4#[.{fingerprint}]?.png","AssetKind":"All","AssetMode":"All","AssetRole":"Primary","AssetMergeBehavior":null,"AssetMergeSource":"","RelatedAsset":null,"AssetTraitName":null,"AssetTraitValue":null,"Fingerprint":"lmady192kq","Integrity":"83LkzNxkY3CaRU58B/cM8aoVLTeerLKlcjqC5qChUq0=","CopyToOutputDirectory":"Never","CopyToPublishDirectory":"PreserveNewest","OriginalItemSpec":"wwwroot\\avatars\\avatar_4.png","FileLength":128386,"LastWriteTime":"2025-07-15T15:45:17.897478+00:00"},"Sv7U6iagZXLI1p7GPVz3LAL8nCai7WWpXWHwJsSPB/E=":{"Identity":"D:\\VSporjects\\Recipix\\Recipix.Server\\wwwroot\\recipe-images\\8de6978f-76ac-443b-9e74-722d1424c2f5.png","SourceId":"Recipix.Server","SourceType":"Discovered","ContentRoot":"D:\\VSporjects\\Recipix\\Recipix.Server\\wwwroot\\","BasePath":"_content/Recipix.Server","RelativePath":"recipe-images/8de6978f-76ac-443b-9e74-722d1424c2f5#[.{fingerprint}]?.png","AssetKind":"All","AssetMode":"All","AssetRole":"Primary","AssetMergeBehavior":null,"AssetMergeSource":"","RelatedAsset":null,"AssetTraitName":null,"AssetTraitValue":null,"Fingerprint":"i8h3svih1e","Integrity":"AlKkWuveAb1BnzaUczsztoWjZ9dMh0sL5uYjtWKlcGg=","CopyToOutputDirectory":"Never","CopyToPublishDirectory":"PreserveNewest","OriginalItemSpec":"wwwroot\\recipe-images\\8de6978f-76ac-443b-9e74-722d1424c2f5.png","FileLength":361865,"LastWriteTime":"2025-07-15T16:04:23.5028086+00:00"},"UwiOoye3wR1BraaIGetbJr/GBibAJJWWdsfrVfpi8Pg=":{"Identity":"D:\\VSporjects\\Recipix\\Recipix.Server\\wwwroot\\avatars\\avatar_5.png","SourceId":"Recipix.Server","SourceType":"Discovered","ContentRoot":"D:\\VSporjects\\Recipix\\Recipix.Server\\wwwroot\\","BasePath":"_content/Recipix.Server","RelativePath":"avatars/avatar_5#[.{fingerprint}]?.png","AssetKind":"All","AssetMode":"All","AssetRole":"Primary","AssetMergeBehavior":null,"AssetMergeSource":"","RelatedAsset":null,"AssetTraitName":null,"AssetTraitValue":null,"Fingerprint":"0dbpwk5l0j","Integrity":"xIWtvcexAM5WRhORUEPeIIGH9euz4/AWozAk6fA5XZQ=","CopyToOutputDirectory":"Never","CopyToPublishDirectory":"PreserveNewest","OriginalItemSpec":"wwwroot\\avatars\\avatar_5.png","FileLength":66478,"LastWriteTime":"2025-07-15T19:48:00.2849593+00:00"},"\u002B\u002B7oypelu9WeychMy56TtSZqnGL9YDtIfMJbyaNiPn8=":{"Identity":"D:\\VSporjects\\Recipix\\Recipix.Server\\wwwroot\\recipe-images\\62031314-2002-4583-b74a-5e31c5f4589f.png","SourceId":"Recipix.Server","SourceType":"Discovered","ContentRoot":"D:\\VSporjects\\Recipix\\Recipix.Server\\wwwroot\\","BasePath":"_content/Recipix.Server","RelativePath":"recipe-images/62031314-2002-4583-b74a-5e31c5f4589f#[.{fingerprint}]?.png","AssetKind":"All","AssetMode":"All","AssetRole":"Primary","AssetMergeBehavior":null,"AssetMergeSource":"","RelatedAsset":null,"AssetTraitName":null,"AssetTraitValue":null,"Fingerprint":"zy9kz47ujp","Integrity":"e/Kljrx2RCR7G4LPn2dHDLpiNRCeGO5jpwCF\u002Bm7PfWg=","CopyToOutputDirectory":"Never","CopyToPublishDirectory":"PreserveNewest","OriginalItemSpec":"wwwroot\\recipe-images\\62031314-2002-4583-b74a-5e31c5f4589f.png","FileLength":334755,"LastWriteTime":"2025-07-15T19:51:04.667165+00:00"},"ztGJJBcjDWIyAQWgMN6htdCZJ30B0AdXI64/5GanZus=":{"Identity":"D:\\VSporjects\\Recipix\\Recipix.Server\\wwwroot\\recipe-images\\1d2a656a-2a8c-4e00-a82b-28bcb77c4a2f.png","SourceId":"Recipix.Server","SourceType":"Discovered","ContentRoot":"D:\\VSporjects\\Recipix\\Recipix.Server\\wwwroot\\","BasePath":"_content/Recipix.Server","RelativePath":"recipe-images/1d2a656a-2a8c-4e00-a82b-28bcb77c4a2f#[.{fingerprint}]?.png","AssetKind":"All","AssetMode":"All","AssetRole":"Primary","AssetMergeBehavior":null,"AssetMergeSource":"","RelatedAsset":null,"AssetTraitName":null,"AssetTraitValue":null,"Fingerprint":"p5xoh2bezw","Integrity":"3eYK0RCGxVpABsFS0NGDHDw2KK\u002BF8iAAKQhgLXXcU4Q=","CopyToOutputDirectory":"Never","CopyToPublishDirectory":"PreserveNewest","OriginalItemSpec":"wwwroot\\recipe-images\\1d2a656a-2a8c-4e00-a82b-28bcb77c4a2f.png","FileLength":488696,"LastWriteTime":"2025-07-15T19:54:13.0079735+00:00"},"XkLQ\u002BvAKJO\u002BGW4flwyNMxSds1bPPmjq6agFVbm6PdDI=":{"Identity":"D:\\VSporjects\\Recipix\\Recipix.Server\\wwwroot\\avatars\\avatar_6.png","SourceId":"Recipix.Server","SourceType":"Discovered","ContentRoot":"D:\\VSporjects\\Recipix\\Recipix.Server\\wwwroot\\","BasePath":"_content/Recipix.Server","RelativePath":"avatars/avatar_6#[.{fingerprint}]?.png","AssetKind":"All","AssetMode":"All","AssetRole":"Primary","AssetMergeBehavior":null,"AssetMergeSource":"","RelatedAsset":null,"AssetTraitName":null,"AssetTraitValue":null,"Fingerprint":"xrgci1qwvv","Integrity":"E4pE43B\u002Bz/XyperGTF1V1eTAEXdZiAGuSxGey/BOdc4=","CopyToOutputDirectory":"Never","CopyToPublishDirectory":"PreserveNewest","OriginalItemSpec":"wwwroot\\avatars\\avatar_6.png","FileLength":147501,"LastWriteTime":"2025-07-15T19:55:10.8905748+00:00"},"qgBhOCuk73FmUWbTmT\u002ByP6oRuBRE2OKpz5Ai9EviJGs=":{"Identity":"D:\\VSporjects\\Recipix\\Recipix.Server\\wwwroot\\recipe-images\\99c522e5-be13-4722-a6b5-54b59f0256c5.png","SourceId":"Recipix.Server","SourceType":"Discovered","ContentRoot":"D:\\VSporjects\\Recipix\\Recipix.Server\\wwwroot\\","BasePath":"_content/Recipix.Server","RelativePath":"recipe-images/99c522e5-be13-4722-a6b5-54b59f0256c5#[.{fingerprint}]?.png","AssetKind":"All","AssetMode":"All","AssetRole":"Primary","AssetMergeBehavior":null,"AssetMergeSource":"","RelatedAsset":null,"AssetTraitName":null,"AssetTraitValue":null,"Fingerprint":"q5000qlfl5","Integrity":"zrjf0Ok1R2IQZom7en1QY9rrTcTkumwT4Y0Bh2hjF7s=","CopyToOutputDirectory":"Never","CopyToPublishDirectory":"PreserveNewest","OriginalItemSpec":"wwwroot\\recipe-images\\99c522e5-be13-4722-a6b5-54b59f0256c5.png","FileLength":429909,"LastWriteTime":"2025-07-15T19:56:12.2594992+00:00"}},"CachedCopyCandidates":{}}